xctype/__init__.py
xctype/stable_prng.py
xctype-0.0.21.dist-info/METADATA
xctype-0.0.21.dist-info/WHEEL
xctype-0.0.21.dist-info/licenses/LICENSE
xctype-0.0.21.dist-info/RECORD
